amsdal_workflow/Third-Party Materials - AMSDAL Dependencies - License Notices.md
amsdal_workflow/__about__.py
amsdal_workflow/__init__.py
amsdal_workflow/app.py
amsdal_workflow/checkpoint.py
amsdal_workflow/py.typed
amsdal_workflow/utils.py
amsdal_workflow/migrations/0000_initial.py
amsdal_workflow/models/__init__.py
amsdal_workflow/models/checkpoint.py
amsdal_workflow/models/checkpoint_writes.py
amsdal_workflow-0.1.0.dist-info/METADATA
amsdal_workflow-0.1.0.dist-info/WHEEL
amsdal_workflow-0.1.0.dist-info/RECORD
