Metadata-Version: 2.4
Name: amsdal_workflow
Version: 0.1.0
Summary: amsdal_workflow plugin for AMSDAL Framework
Requires-Python: >=3.11
Requires-Dist: amsdal[cli]>=0.5.14
Requires-Dist: langgraph>=0.6.8
Provides-Extra: openai
Requires-Dist: langchain[openai]; extra == 'openai'
